{"resourceType":"StructureMap","id":"ClinicalImpression4Bto5","text":{"status":"generated","div":"<div xmlns=\"http://www.w3.org/1999/xhtml\"><pre class=\"fml\">\r\n<span style=\"color: #cc00cc\">/// <b>url</b> = </span><span style=\"color: blue\">'http://hl7.org/fhir/StructureMap/ClinicalImpression4Bto5'</span>\r\n<span style=\"color: #cc00cc\">/// <b>name</b> = </span><span style=\"color: blue\">'ClinicalImpression4Bto5'</span>\r\n<span style=\"color: #cc00cc\">/// <b>title</b> = </span><span style=\"color: blue\">'FML Conversion for ClinicalImpression: R4B to R5'</span>\r\n<span style=\"color: #cc00cc\">/// <b>status</b> = </span><span style=\"color: blue\">'draft'</span>\r\n\r\n<b>conceptmap</b><span style=\"color: navy\"> &quot;</span>ClinicalImpressionStatus<span style=\"color: navy\">&quot; {\r\n</span><b>  prefix </b>s<span style=\"color: navy\"> = &quot;</span><a href=\"http://hl7.org/fhir/R4B/codesystem-event-status.html\" title=\"EventStatus\">http://hl7.org/fhir/4.3/event-status</a><span style=\"color: navy\">&quot;\r\n</span><b>  prefix </b>t<span style=\"color: navy\"> = &quot;</span><a href=\"http://hl7.org/fhir/R5/codesystem-event-status.html\" title=\"EventStatus\">http://hl7.org/fhir/event-status</a><span style=\"color: navy\">&quot;\r\n</span>\r\n  s<span style=\"color: navy\">:</span>preparation <b>-</b> t<span style=\"color: navy\">:</span>preparation\r\n  s<span style=\"color: navy\">:</span>&quot;in-progress&quot; <b>-</b> t<span style=\"color: navy\">:</span><span style=\"color: navy\">&quot;</span>in-progress<span style=\"color: navy\">&quot;</span>\r\n  s<span style=\"color: navy\">:</span>&quot;not-done&quot; <b>-</b> t<span style=\"color: navy\">:</span><span style=\"color: navy\">&quot;</span>not-done<span style=\"color: navy\">&quot;</span>\r\n  s<span style=\"color: navy\">:</span>&quot;on-hold&quot; <b>-</b> t<span style=\"color: navy\">:</span><span style=\"color: navy\">&quot;</span>on-hold<span style=\"color: navy\">&quot;</span>\r\n  s<span style=\"color: navy\">:</span>stopped <b>-</b> t<span style=\"color: navy\">:</span>stopped\r\n  s<span style=\"color: navy\">:</span>completed <b>-</b> t<span style=\"color: navy\">:</span>completed\r\n  s<span style=\"color: navy\">:</span>&quot;entered-in-error&quot; <b>-</b> t<span style=\"color: navy\">:</span><span style=\"color: navy\">&quot;</span>entered-in-error<span style=\"color: navy\">&quot;</span>\r\n  s<span style=\"color: navy\">:</span>unknown <b>-</b> t<span style=\"color: navy\">:</span>unknown\r\n<span style=\"color: navy\">}\r\n\r\n</span><b>uses</b><span style=\"color: navy\"> &quot;</span><a href=\"http://hl7.org/fhir/R4B/clinicalimpression.html\" title=\"ClinicalImpression\">http://hl7.org/fhir/4.3/StructureDefinition/ClinicalImpression</a><span style=\"color: navy\">&quot; </span><b>alias </b>ClinicalImpressionR4B <b>as </b><b>source</b>\r\n<b>uses</b><span style=\"color: navy\"> &quot;</span><a href=\"http://hl7.org/fhir/R5/clinicalimpression.html\" title=\"ClinicalImpression\">http://hl7.org/fhir/StructureDefinition/ClinicalImpression</a><span style=\"color: navy\">&quot; </span><b>alias </b>ClinicalImpressionR5 <b>as </b><b>target</b>\r\n\r\n<b>imports</b><span style=\"color: navy\"> &quot;</span>http://hl7.org/fhir/StructureMap/*4Bto5<span style=\"color: navy\">&quot;\r\n</span>\r\n<b>group </b>ClinicalImpression<span style=\"color: navy\">(</span><b>source</b> <span style=\"color: maroon\">src</span><span style=\"color: navy\"> : </span>ClinicalImpressionR4B, <b>target</b> <span style=\"color: maroon\">tgt</span><span style=\"color: navy\"> : </span>ClinicalImpressionR5<span style=\"color: navy\">)</span><b> extends </b>DomainResource<b> &lt;&lt;type+&gt;&gt;</b><span style=\"color: navy\"> {\r\n</span>  src.identifier<span style=\"color: navy\"><b> -&gt; </b></span>tgt.identifier<span style=\"color: navy\">;</span>\r\n  src.status<b> as </b><span style=\"color: maroon\">v</span><span style=\"color: navy\"><b> -&gt; </b></span>tgt.status = <b>translate</b><span style=\"color: navy\">(</span><span style=\"color: maroon\">v</span><span style=\"color: navy\">, </span><span style=\"color: blue\">'#ClinicalImpressionStatus'</span><span style=\"color: navy\">, </span><span style=\"color: blue\">'code'</span><span style=\"color: navy\">)</span><span style=\"color: navy\">;</span>\r\n  src.statusReason<span style=\"color: navy\"><b> -&gt; </b></span>tgt.statusReason<span style=\"color: navy\">;</span>\r\n  src.description<span style=\"color: navy\"><b> -&gt; </b></span>tgt.description<span style=\"color: navy\">;</span>\r\n  src.subject<span style=\"color: navy\"><b> -&gt; </b></span>tgt.subject<span style=\"color: navy\">;</span>\r\n  src.encounter<span style=\"color: navy\"><b> -&gt; </b></span>tgt.encounter<span style=\"color: navy\">;</span>\r\n  src.effective<span style=\"color: navy\"> : </span>dateTime<span style=\"color: navy\"><b> -&gt; </b></span>tgt.effective<span style=\"color: navy\">;</span>\r\n  src.effective<span style=\"color: navy\"> : </span>Period<span style=\"color: navy\"><b> -&gt; </b></span>tgt.effective<span style=\"color: navy\">;</span>\r\n  src.date<span style=\"color: navy\"><b> -&gt; </b></span>tgt.date<span style=\"color: navy\">;</span>\r\n  src.assessor<span style=\"color: navy\"><b> -&gt; </b></span>tgt.performer<span style=\"color: navy\">;</span>\r\n  src.previous<span style=\"color: navy\"><b> -&gt; </b></span>tgt.previous<span style=\"color: navy\">;</span>\r\n  src.problem<span style=\"color: navy\"><b> -&gt; </b></span>tgt.problem<span style=\"color: navy\">;</span>\r\n  src.protocol<span style=\"color: navy\"><b> -&gt; </b></span>tgt.protocol<span style=\"color: navy\">;</span> <span style=\"color: navy\">// </span><span style=\"color: green\">src.changePattern -&gt; tgt.changePattern;</span>\r\n  src.summary<span style=\"color: navy\"><b> -&gt; </b></span>tgt.summary<span style=\"color: navy\">;</span>\r\n  src.finding<b> as </b><span style=\"color: maroon\">s</span><span style=\"color: navy\"><b> -&gt; </b></span>tgt.finding<b> as </b><span style=\"color: maroon\">t</span><b> then </b>ClinicalImpressionFinding<span style=\"color: navy\">(</span><span style=\"color: maroon\">s</span><span style=\"color: navy\">, </span><span style=\"color: maroon\">t</span><span style=\"color: navy\">)</span><span style=\"color: navy\">;</span>\r\n  src.prognosisCodeableConcept<span style=\"color: navy\"><b> -&gt; </b></span>tgt.prognosisCodeableConcept<span style=\"color: navy\">;</span>\r\n  src.prognosisReference<span style=\"color: navy\"><b> -&gt; </b></span>tgt.prognosisReference<span style=\"color: navy\">;</span>\r\n  src.supportingInfo<span style=\"color: navy\"><b> -&gt; </b></span>tgt.supportingInfo<span style=\"color: navy\">;</span>\r\n  src.note<span style=\"color: navy\"><b> -&gt; </b></span>tgt.note<span style=\"color: navy\">;</span>\r\n<span style=\"color: navy\">}\r\n\r\n</span><b>group </b>ClinicalImpressionFinding<span style=\"color: navy\">(</span><b>source</b> <span style=\"color: maroon\">src</span>, <b>target</b> <span style=\"color: maroon\">tgt</span><span style=\"color: navy\">)</span><b> extends </b>BackboneElement<span style=\"color: navy\"> {\r\n</span>  src.itemCodeableConcept<span style=\"color: navy\"><b> -&gt; </b></span>tgt.item<span style=\"color: navy\">;</span>\r\n  src.itemReference<span style=\"color: navy\"><b> -&gt; </b></span>tgt.item<span style=\"color: navy\">;</span>\r\n  src.basis<span style=\"color: navy\"><b> -&gt; </b></span>tgt.basis<span style=\"color: navy\">;</span>\r\n<span style=\"color: navy\">}\r\n\r\n</span></pre></div>"},"contained":[{"resourceType":"ConceptMap","id":"ClinicalImpressionStatus","status":"draft","group":[{"source":"http://hl7.org/fhir/4.3/event-status","target":"http://hl7.org/fhir/event-status","element":[{"code":"preparation","target":[{"code":"preparation","equivalence":"relatedto"}]},{"code":"in-progress","target":[{"code":"in-progress","equivalence":"relatedto"}]},{"code":"not-done","target":[{"code":"not-done","equivalence":"relatedto"}]},{"code":"on-hold","target":[{"code":"on-hold","equivalence":"relatedto"}]},{"code":"stopped","target":[{"code":"stopped","equivalence":"relatedto"}]},{"code":"completed","target":[{"code":"completed","equivalence":"relatedto"}]},{"code":"entered-in-error","target":[{"code":"entered-in-error","equivalence":"relatedto"}]},{"code":"unknown","target":[{"code":"unknown","equivalence":"relatedto"}]}]}]}],"extension":[{"url":"http://hl7.org/fhir/StructureDefinition/structuredefinition-wg","valueCode":"fhir"},{"url":"http://hl7.org/fhir/StructureDefinition/structuredefinition-fmm","valueInteger":1,"_valueInteger":{"extension":[{"url":"http://hl7.org/fhir/StructureDefinition/structuredefinition-conformance-derivedFrom","valueCanonical":"http://hl7.org/fhir/extensions/ImplementationGuide/hl7.fhir.uv.extensions"}]}},{"url":"http://hl7.org/fhir/StructureDefinition/structuredefinition-standards-status","valueCode":"trial-use","_valueCode":{"extension":[{"url":"http://hl7.org/fhir/StructureDefinition/structuredefinition-conformance-derivedFrom","valueCanonical":"http://hl7.org/fhir/extensions/ImplementationGuide/hl7.fhir.uv.extensions"}]}}],"url":"http://hl7.org/fhir/StructureMap/ClinicalImpression4Bto5","version":"5.1.0","name":"ClinicalImpression4Bto5","title":"FML Conversion for ClinicalImpression: R4B to R5","status":"draft","date":"2024-04-27T18:40:24+10:00","publisher":"HL7 International / FHIR Infrastructure","contact":[{"telecom":[{"system":"url","value":"http://www.hl7.org/Special/committees/fiwg"}]}],"description":"FMLConversionforClinicalImpressionR4BtoR5","jurisdiction":[{"coding":[{"system":"http://unstats.un.org/unsd/methods/m49/m49.htm","code":"001"}]}],"structure":[{"url":"http://hl7.org/fhir/4.3/StructureDefinition/ClinicalImpression","mode":"source","alias":"ClinicalImpressionR4B"},{"url":"http://hl7.org/fhir/StructureDefinition/ClinicalImpression","mode":"target","alias":"ClinicalImpressionR5"}],"import":["http://hl7.org/fhir/StructureMap/*4Bto5"],"group":[{"name":"ClinicalImpression","extends":"DomainResource","typeMode":"type-and-types","input":[{"name":"src","type":"ClinicalImpressionR4B","mode":"source"},{"name":"tgt","type":"ClinicalImpressionR5","mode":"target"}],"rule":[{"name":"identifier","source":[{"context":"src","element":"identifier","variable":"vvv"}],"target":[{"context":"tgt","contextType":"variable","element":"identifier","variable":"vvv","transform":"create"}],"dependent":[{"name":"DefaultMappingGroupAnonymousAlias","variable":["vvv","vvv"]}]},{"name":"status","source":[{"context":"src","element":"status","variable":"v"}],"target":[{"context":"tgt","contextType":"variable","element":"status","transform":"translate","parameter":[{"valueId":"v"},{"valueString":"#ClinicalImpressionStatus"},{"valueString":"code"}]}]},{"name":"statusReason","source":[{"context":"src","element":"statusReason","variable":"vvv"}],"target":[{"context":"tgt","contextType":"variable","element":"statusReason","variable":"vvv","transform":"create"}],"dependent":[{"name":"DefaultMappingGroupAnonymousAlias","variable":["vvv","vvv"]}]},{"name":"description","source":[{"context":"src","element":"description","variable":"vvv"}],"target":[{"context":"tgt","contextType":"variable","element":"description","variable":"vvv","transform":"create"}],"dependent":[{"name":"DefaultMappingGroupAnonymousAlias","variable":["vvv","vvv"]}]},{"name":"subject","source":[{"context":"src","element":"subject","variable":"vvv"}],"target":[{"context":"tgt","contextType":"variable","element":"subject","variable":"vvv","transform":"create"}],"dependent":[{"name":"DefaultMappingGroupAnonymousAlias","variable":["vvv","vvv"]}]},{"name":"encounter","source":[{"context":"src","element":"encounter","variable":"vvv"}],"target":[{"context":"tgt","contextType":"variable","element":"encounter","variable":"vvv","transform":"create"}],"dependent":[{"name":"DefaultMappingGroupAnonymousAlias","variable":["vvv","vvv"]}]},{"name":"effectiveDateTime","source":[{"context":"src","type":"dateTime","element":"effective","variable":"vvv"}],"target":[{"context":"tgt","contextType":"variable","element":"effective","variable":"vvv","transform":"create"}],"dependent":[{"name":"DefaultMappingGroupAnonymousAlias","variable":["vvv","vvv"]}]},{"name":"effectivePeriod","source":[{"context":"src","type":"Period","element":"effective","variable":"vvv"}],"target":[{"context":"tgt","contextType":"variable","element":"effective","variable":"vvv","transform":"create"}],"dependent":[{"name":"DefaultMappingGroupAnonymousAlias","variable":["vvv","vvv"]}]},{"name":"date","source":[{"context":"src","element":"date","variable":"vvv"}],"target":[{"context":"tgt","contextType":"variable","element":"date","variable":"vvv","transform":"create"}],"dependent":[{"name":"DefaultMappingGroupAnonymousAlias","variable":["vvv","vvv"]}]},{"name":"assessor","source":[{"context":"src","element":"assessor","variable":"vvv"}],"target":[{"context":"tgt","contextType":"variable","element":"performer","variable":"vvv","transform":"create"}],"dependent":[{"name":"DefaultMappingGroupAnonymousAlias","variable":["vvv","vvv"]}]},{"name":"previous","source":[{"context":"src","element":"previous","variable":"vvv"}],"target":[{"context":"tgt","contextType":"variable","element":"previous","variable":"vvv","transform":"create"}],"dependent":[{"name":"DefaultMappingGroupAnonymousAlias","variable":["vvv","vvv"]}]},{"name":"problem","source":[{"context":"src","element":"problem","variable":"vvv"}],"target":[{"context":"tgt","contextType":"variable","element":"problem","variable":"vvv","transform":"create"}],"dependent":[{"name":"DefaultMappingGroupAnonymousAlias","variable":["vvv","vvv"]}]},{"name":"protocol","source":[{"context":"src","element":"protocol","variable":"vvv"}],"target":[{"context":"tgt","contextType":"variable","element":"protocol","variable":"vvv","transform":"create"}],"dependent":[{"name":"DefaultMappingGroupAnonymousAlias","variable":["vvv","vvv"]}],"documentation":"src.changePattern -> tgt.changePattern;"},{"name":"summary","source":[{"context":"src","element":"summary","variable":"vvv"}],"target":[{"context":"tgt","contextType":"variable","element":"summary","variable":"vvv","transform":"create"}],"dependent":[{"name":"DefaultMappingGroupAnonymousAlias","variable":["vvv","vvv"]}]},{"name":"finding","source":[{"context":"src","element":"finding","variable":"s"}],"target":[{"context":"tgt","contextType":"variable","element":"finding","variable":"t"}],"dependent":[{"name":"ClinicalImpressionFinding","variable":["s","t"]}]},{"name":"prognosisCodeableConcept","source":[{"context":"src","element":"prognosisCodeableConcept","variable":"vvv"}],"target":[{"context":"tgt","contextType":"variable","element":"prognosisCodeableConcept","variable":"vvv","transform":"create"}],"dependent":[{"name":"DefaultMappingGroupAnonymousAlias","variable":["vvv","vvv"]}]},{"name":"prognosisReference","source":[{"context":"src","element":"prognosisReference","variable":"vvv"}],"target":[{"context":"tgt","contextType":"variable","element":"prognosisReference","variable":"vvv","transform":"create"}],"dependent":[{"name":"DefaultMappingGroupAnonymousAlias","variable":["vvv","vvv"]}]},{"name":"supportingInfo","source":[{"context":"src","element":"supportingInfo","variable":"vvv"}],"target":[{"context":"tgt","contextType":"variable","element":"supportingInfo","variable":"vvv","transform":"create"}],"dependent":[{"name":"DefaultMappingGroupAnonymousAlias","variable":["vvv","vvv"]}]},{"name":"note","source":[{"context":"src","element":"note","variable":"vvv"}],"target":[{"context":"tgt","contextType":"variable","element":"note","variable":"vvv","transform":"create"}],"dependent":[{"name":"DefaultMappingGroupAnonymousAlias","variable":["vvv","vvv"]}]}]},{"name":"ClinicalImpressionFinding","extends":"BackboneElement","typeMode":"none","input":[{"name":"src","mode":"source"},{"name":"tgt","mode":"target"}],"rule":[{"name":"itemCodeableConcept","source":[{"context":"src","element":"itemCodeableConcept","variable":"vvv"}],"target":[{"context":"tgt","contextType":"variable","element":"item","variable":"vvv","transform":"create"}],"dependent":[{"name":"DefaultMappingGroupAnonymousAlias","variable":["vvv","vvv"]}]},{"name":"itemReference","source":[{"context":"src","element":"itemReference","variable":"vvv"}],"target":[{"context":"tgt","contextType":"variable","element":"item","variable":"vvv","transform":"create"}],"dependent":[{"name":"DefaultMappingGroupAnonymousAlias","variable":["vvv","vvv"]}]},{"name":"basis","source":[{"context":"src","element":"basis","variable":"vvv"}],"target":[{"context":"tgt","contextType":"variable","element":"basis","variable":"vvv","transform":"create"}],"dependent":[{"name":"DefaultMappingGroupAnonymousAlias","variable":["vvv","vvv"]}]}]}]}